drolta/Drolta.g4
drolta/__init__.py
drolta/ast.py
drolta/data.py
drolta/db.py
drolta/engine.py
drolta/errors.py
drolta/interpreter.py
drolta/py.typed
drolta/parsing/Drolta.interp
drolta/parsing/Drolta.tokens
drolta/parsing/DroltaLexer.interp
drolta/parsing/DroltaLexer.py
drolta/parsing/DroltaLexer.tokens
drolta/parsing/DroltaListener.py
drolta/parsing/DroltaParser.py
drolta/parsing/__init__.py
drolta-0.4.2.dist-info/METADATA
drolta-0.4.2.dist-info/WHEEL
drolta-0.4.2.dist-info/licenses/LICENSE
drolta-0.4.2.dist-info/RECORD
