Metadata-Version: 2.4
Name: drolta
Version: 0.4.2
Summary: A SQLite query engine for simplified, composable, and declarative queries.
Project-URL: Homepage, https://github.com/ShiJbey/drolta_py/
Project-URL: History, https://github.com/ShiJbey/drolta_py/CHANGELOG.md
Project-URL: Tracker, https://github.com/ShiJbey/drolta_py/issues
Project-URL: Source, https://github.com/ShiJbey/drolta_py/
Author-email: Shi Johnson-Bey <shijbey@gmail.com>
License-Expression: MIT
License-File: LICENSE
Keywords: database,drolta,query engine,querying,sqlite
Classifier: Intended Audience :: Developers
Classifier: License :: OSI Approved :: MIT License
Classifier: Operating System :: OS Independent
Classifier: Programming Language :: Python :: 3.9
Classifier: Programming Language :: Python :: 3.10
Classifier: Programming Language :: Python :: 3.11
Classifier: Programming Language :: Python :: 3.12
Classifier: Programming Language :: Python :: 3.13
Classifier: Programming Language :: SQL
Classifier: Topic :: Database
Classifier: Topic :: Database :: Database Engines/Servers
Requires-Python: >=3.9
Requires-Dist: antlr4-python3-runtime>=4.13.2
Requires-Dist: attrs>=25.1.0
Requires-Dist: sqlparse>=0.5.3
Provides-Extra: development
Requires-Dist: antlr4-tools; extra == 'development'
Requires-Dist: black; extra == 'development'
Requires-Dist: build; extra == 'development'
Requires-Dist: hatchling; extra == 'development'
Requires-Dist: isort; extra == 'development'
Requires-Dist: pytest; extra == 'development'
